kineticemail/__init__.py
kineticemail-0.0.11.dist-info/METADATA
kineticemail-0.0.11.dist-info/WHEEL
kineticemail-0.0.11.dist-info/top_level.txt
kineticemail-0.0.11.dist-info/RECORD
